termpix/__init__.py
termpix/demo.png
termpix/demo.py
termpix/requirements.txt
termpix/termpix.py
termpix/today.sh
termpix-0.5.3.dist-info/METADATA
termpix-0.5.3.dist-info/WHEEL
termpix-0.5.3.dist-info/entry_points.txt
termpix-0.5.3.dist-info/top_level.txt
termpix-0.5.3.dist-info/RECORD
