Metadata-Version: 2.1
Name: termpix
Version: 0.5.3
Summary: This program play video by tty and capable to output video into text file.
Home-page: https://github.com/Erickrus/termpix
Author: Hu, Ying-Hao
Author-email: hyinghao@hotmail.com
License: Apache
Project-URL: Maintainer Repository, https://github.com/tjnh05/termpix
Keywords: termpix,terminal,tty,video
Platform: any
Classifier: Programming Language :: Python :: 3
Classifier: License :: OSI Approved :: Apache Software License
Classifier: Operating System :: OS Independent
Requires-Python: >=3.5.2
Requires-Dist: numpy
Requires-Dist: urllib3
Requires-Dist: Pillow
Requires-Dist: imageio
Requires-Dist: imageio-ffmpeg
Requires-Dist: PyAudio
